odoo10_addon_account_banking_reconciliation-10.0.1.0.0.99.dev20-nspkg.pth
odoo/addons/account_banking_reconciliation/README.rst
odoo/addons/account_banking_reconciliation/__init__.py
odoo/addons/account_banking_reconciliation/__manifest__.py
odoo/addons/account_banking_reconciliation/i18n/account_banking_reconciliation.pot
odoo/addons/account_banking_reconciliation/i18n/es_EC.po
odoo/addons/account_banking_reconciliation/models/__init__.py
odoo/addons/account_banking_reconciliation/models/account_banking_reconciliation.py
odoo/addons/account_banking_reconciliation/models/account_move_line.py
odoo/addons/account_banking_reconciliation/report/bank_statement_report.xml
odoo/addons/account_banking_reconciliation/security/account_banking_reconciliation.xml
odoo/addons/account_banking_reconciliation/security/ir.model.access.csv
odoo/addons/account_banking_reconciliation/static/description/icon.png
odoo/addons/account_banking_reconciliation/views/account_banking_reconciliation.xml
odoo/addons/account_banking_reconciliation/views/account_move_line.xml
odoo/addons/account_banking_reconciliation/views/report_bank_statement_detail.xml
odoo/addons/account_banking_reconciliation/views/report_bank_statement_summary.xml
odoo10_addon_account_banking_reconciliation-10.0.1.0.0.99.dev20.dist-info/METADATA
odoo10_addon_account_banking_reconciliation-10.0.1.0.0.99.dev20.dist-info/WHEEL
odoo10_addon_account_banking_reconciliation-10.0.1.0.0.99.dev20.dist-info/namespace_packages.txt
odoo10_addon_account_banking_reconciliation-10.0.1.0.0.99.dev20.dist-info/top_level.txt
odoo10_addon_account_banking_reconciliation-10.0.1.0.0.99.dev20.dist-info/RECORD
